icloudpy/__init__.py
icloudpy/base.py
icloudpy/cmdline.py
icloudpy/exceptions.py
icloudpy/utils.py
icloudpy/services/__init__.py
icloudpy/services/account.py
icloudpy/services/calendar.py
icloudpy/services/contacts.py
icloudpy/services/drive.py
icloudpy/services/findmyiphone.py
icloudpy/services/photos.py
icloudpy/services/reminders.py
icloudpy/services/ubiquity.py
lns_icloudpy-0.0.3.dist-info/LICENSE
lns_icloudpy-0.0.3.dist-info/METADATA
lns_icloudpy-0.0.3.dist-info/WHEEL
lns_icloudpy-0.0.3.dist-info/entry_points.txt
lns_icloudpy-0.0.3.dist-info/top_level.txt
lns_icloudpy-0.0.3.dist-info/RECORD
